quantinfra/__init__.py
quantinfra-0.0.1.dist-info/METADATA
quantinfra-0.0.1.dist-info/WHEEL
quantinfra-0.0.1.dist-info/licenses/LICENSE
quantinfra-0.0.1.dist-info/RECORD
