Metadata-Version: 2.4
Name: quantinfra
Version: 0.0.1
Summary: QuantInfra SDK for Python
Author-email: QuantInfra <support@quantinfra.com>
License: 
License-File: LICENSE
Requires-Python: >=3.8
